LICENSE
MANIFEST.in
README.md
README_zh_CN.md
setup.py
docs/API.md
docs/zh_CN/API.md
docs/zh_CN/CONTRIBUTING.md
examples/bucket_exists.py
examples/fget_object.py
examples/fput_object.py
examples/get_object.py
examples/list_objects.py
examples/progress.py
examples/put_object.py
examples/remove_object.py
examples/stat_object.py
newtera/__init__.py
newtera/api.py
newtera/datatypes.py
newtera/error.py
newtera/helpers.py
newtera/py.typed
newtera/xml.py
newtera.egg-info/PKG-INFO
newtera.egg-info/SOURCES.txt
newtera.egg-info/dependency_links.txt
newtera.egg-info/requires.txt
newtera.egg-info/top_level.txt
newtera/credentials/__init__.py
newtera/credentials/credentials.py
newtera/credentials/providers.py
tests/certs/private.key
tests/certs/public.crt
tests/functional/play.min.io.kes.root.key
tests/unit/config.json.sample