Metadata-Version: 2.1
Name: newtera
Version: 1.0.0
Summary: Newtera Python SDK for Newtera TDM
Home-page: https://github.com/yong-zhang-newtera/newtera-py
Author: Newtera
Author-email: info@newtera.com
License: Apache-2.0
Classifier: Development Status :: 5 - Production/Stable
Classifier: Intended Audience :: Developers
Classifier: License :: OSI Approved :: Apache Software License
Classifier: Natural Language :: English
Classifier: Operating System :: OS Independent
Classifier: Programming Language :: Python
Classifier: Programming Language :: Python :: 3.7
Classifier: Programming Language :: Python :: 3.8
Classifier: Programming Language :: Python :: 3.9
Classifier: Programming Language :: Python :: 3.10
Classifier: Programming Language :: Python :: 3.11
Classifier: Topic :: Software Development :: Libraries :: Python Modules
License-File: LICENSE
Requires-Dist: urllib3
Requires-Dist: typing-extensions
